bitfield.py
motorengine_bitfield-1.0.0.dist-info/DESCRIPTION.rst
motorengine_bitfield-1.0.0.dist-info/METADATA
motorengine_bitfield-1.0.0.dist-info/RECORD
motorengine_bitfield-1.0.0.dist-info/WHEEL
motorengine_bitfield-1.0.0.dist-info/metadata.json
motorengine_bitfield-1.0.0.dist-info/top_level.txt
