Metadata-Version: 2.0
Name: motorengine-bitfield
Version: 1.0.0
Summary: Custom field type for storing and retrieving bit-packed flags as enums.
Home-page: https://gitlab.com/wmedlar/motorengine-bitfield
Author: Will Medlar
Author-email: UNKNOWN
License: GPLv3
Keywords: motorengine bit-packing enum
Platform: any
Classifier: Development Status :: 4 - Beta
Classifier: Intended Audience :: Developers
Classifier: License :: OSI Approved :: GNU General Public License v3 (GPLv3)
Classifier: Operating System :: OS Independent
Classifier: Programming Language :: Python :: 3.6
Classifier: Topic :: Database :: Database Engines/Servers
Requires-Python: >=3.6
Requires-Dist: motorengine (<1,>=0.9)
